<annotation><filename>color_2.jpg</filename><folder>users/zhou338//instrument</folder><source><submittedBy>Tian Zhou</submittedBy></source><imagesize><nrows>370</nrows><ncols>553</ncols></imagesize><object><name>scalpel</name><deleted>0</deleted><verified>0</verified><occluded>no</occluded><attributes></attributes><parts><hasparts></hasparts><ispartof></ispartof></parts><date>14-Jan-2016 07:50:32</date><id>0</id><polygon><username>tzhou</username><pt><x>45</x><y>33</y></pt><pt><x>222</x><y>37</y></pt><pt><x>226</x><y>70</y></pt><pt><x>45</x><y>66</y></pt></polygon></object><object><name>hemostat</name><deleted>0</deleted><verified>0</verified><occluded>no</occluded><attributes></attributes><parts><hasparts></hasparts><ispartof></ispartof></parts><date>14-Jan-2016 07:50:59</date><id>1</id><polygon><username>tzhou</username><pt><x>68</x><y>113</y></pt><pt><x>52</x><y>148</y></pt><pt><x>37</x><y>256</y></pt><pt><x>11</x><y>265</y></pt><pt><x>11</x><y>286</y></pt><pt><x>23</x><y>301</y></pt><pt><x>35</x><y>295</y></pt><pt><x>53</x><y>323</y></pt><pt><x>77</x><y>334</y></pt><pt><x>104</x><y>327</y></pt><pt><x>132</x><y>332</y></pt><pt><x>154</x><y>325</y></pt><pt><x>163</x><y>299</y></pt><pt><x>149</x><y>293</y></pt><pt><x>146</x><y>279</y></pt><pt><x>169</x><y>155</y></pt><pt><x>184</x><y>118</y></pt></polygon></object><object><name>scissors</name><deleted>0</deleted><verified>0</verified><occluded>no</occluded><attributes></attributes><parts><hasparts></hasparts><ispartof></ispartof></parts><date>14-Jan-2016 07:51:16</date><id>2</id><polygon><username>tzhou</username><pt><x>237</x><y>157</y></pt><pt><x>287</x><y>163</y></pt><pt><x>271</x><y>268</y></pt><pt><x>280</x><y>292</y></pt><pt><x>278</x><y>307</y></pt><pt><x>241</x><y>313</y></pt><pt><x>231</x><y>304</y></pt><pt><x>217</x><y>284</y></pt><pt><x>221</x><y>269</y></pt><pt><x>229</x><y>266</y></pt></polygon></object><object><name>allis</name><deleted>0</deleted><verified>0</verified><occluded>no</occluded><attributes></attributes><parts><hasparts></hasparts><ispartof></ispartof></parts><date>14-Jan-2016 07:51:30</date><id>3</id><polygon><username>tzhou</username><pt><x>362</x><y>130</y></pt><pt><x>362</x><y>271</y></pt><pt><x>356</x><y>283</y></pt><pt><x>367</x><y>326</y></pt><pt><x>387</x><y>340</y></pt><pt><x>425</x><y>340</y></pt><pt><x>437</x><y>335</y></pt><pt><x>433</x><y>300</y></pt><pt><x>445</x><y>137</y></pt></polygon></object><object><name>retractor</name><deleted>0</deleted><verified>0</verified><occluded>no</occluded><attributes></attributes><parts><hasparts></hasparts><ispartof></ispartof></parts><date>14-Jan-2016 07:51:51</date><id>4</id><polygon><username>tzhou</username><pt><x>304</x><y>45</y></pt><pt><x>305</x><y>23</y></pt><pt><x>335</x><y>18</y></pt><pt><x>339</x><y>41</y></pt><pt><x>368</x><y>58</y></pt><pt><x>387</x><y>48</y></pt><pt><x>428</x><y>62</y></pt><pt><x>456</x><y>59</y></pt><pt><x>450</x><y>84</y></pt><pt><x>426</x><y>82</y></pt><pt><x>387</x><y>91</y></pt><pt><x>362</x><y>79</y></pt><pt><x>349</x><y>107</y></pt><pt><x>314</x><y>113</y></pt><pt><x>298</x><y>91</y></pt><pt><x>322</x><y>74</y></pt><pt><x>337</x><y>72</y></pt><pt><x>339</x><y>58</y></pt></polygon></object></annotation>